conduit_jupyter_kernel_provisioner-0.1.0.dist-info/licenses/LICENSE
cspyk/__init__.py
cspyk/devtunnel.py
cspyk/kernelapp.py
cspyk/provisioning.py
cspyk/provisioning_local.py
conduit_jupyter_kernel_provisioner-0.1.0.dist-info/METADATA
conduit_jupyter_kernel_provisioner-0.1.0.dist-info/WHEEL
conduit_jupyter_kernel_provisioner-0.1.0.dist-info/entry_points.txt
conduit_jupyter_kernel_provisioner-0.1.0.dist-info/top_level.txt
conduit_jupyter_kernel_provisioner-0.1.0.dist-info/RECORD
